dcxml/__init__.py
dcxml/simpledc.py
dcxml/version.py
dcxml/xmlutils.py
dcxml-0.1.2.dist-info/AUTHORS.rst
dcxml-0.1.2.dist-info/LICENSE
dcxml-0.1.2.dist-info/METADATA
dcxml-0.1.2.dist-info/WHEEL
dcxml-0.1.2.dist-info/top_level.txt
dcxml-0.1.2.dist-info/RECORD
