Metadata-Version: 2.1
Name: dcxml
Version: 0.1.2
Summary: Dublin Core XML generation from Python dictionaries.
Home-page: https://github.com/inveniosoftware/dcxml
Author: CERN
Author-email: info@inveniosoftware.org
License: MIT
Keywords: dublin core xml json
Platform: any
Classifier: Environment :: Web Environment
Classifier: Intended Audience :: Developers
Classifier: License :: OSI Approved :: MIT License
Classifier: Operating System :: OS Independent
Classifier: Programming Language :: Python
Classifier: Topic :: Software Development :: Libraries :: Python Modules
Classifier: Programming Language :: Python :: 3
Classifier: Programming Language :: Python :: 3.6
Classifier: Programming Language :: Python :: 3.7
Classifier: Development Status :: 5 - Production/Stable
Requires-Dist: lxml (>=4.1.1)
Provides-Extra: all
Requires-Dist: Sphinx (>=1.5.2) ; extra == 'all'
Requires-Dist: check-manifest (>=0.25) ; extra == 'all'
Requires-Dist: coverage (>=4.0) ; extra == 'all'
Requires-Dist: isort (>=4.2.2) ; extra == 'all'
Requires-Dist: pydocstyle (>=1.0.0) ; extra == 'all'
Requires-Dist: pytest-cov (>=1.8.0) ; extra == 'all'
Requires-Dist: pytest-pep8 (>=1.0.6) ; extra == 'all'
Requires-Dist: pytest (>=2.8.0) ; extra == 'all'
Provides-Extra: docs
Requires-Dist: Sphinx (>=1.5.2) ; extra == 'docs'
Provides-Extra: tests
Requires-Dist: check-manifest (>=0.25) ; extra == 'tests'
Requires-Dist: coverage (>=4.0) ; extra == 'tests'
Requires-Dist: isort (>=4.2.2) ; extra == 'tests'
Requires-Dist: pydocstyle (>=1.0.0) ; extra == 'tests'
Requires-Dist: pytest-cov (>=1.8.0) ; extra == 'tests'
Requires-Dist: pytest-pep8 (>=1.0.6) ; extra == 'tests'
Requires-Dist: pytest (>=2.8.0) ; extra == 'tests'
